{"00h": {"temp": "11.7", "precip": "0", "vent": "11", "rafales": "25.9", "hum": "93", "t_res": "NaN", "rad": "NaN", "rose": "10.6", "pression": "1017.1", "visi": "19"}, "23h": {"temp": "11.9", "precip": "2.8", "vent": "7", "rafales": "32.4", "hum": "96", "t_res": "NaN", "rad": "NaN", "rose": "11.3", "pression": "1016.7", "visi": "2.1"}, "22h": {"temp": "12.8", "precip": "1.4", "vent": "14", "rafales": "35.3", "hum": "94", "t_res": "NaN", "rad": "NaN", "rose": "11.9", "pression": "1016.4", "visi": "3.6"}, "21h": {"temp": "13.5", "precip": "0.4", "vent": "11", "rafales": "27.7", "hum": "94", "t_res": "NaN", "rad": "NaN", "rose": "12.6", "pression": "1015.9", "visi": "11"}, "20h": {"temp": "13.6", "precip": "0.2", "vent": "11", "rafales": "27", "hum": "94", "t_res": "NaN", "rad": "NaN", "rose": "12.7", "pression": "1015.9", "visi": "7"}, "19h": {"temp": "13.8", "precip": "0.8", "vent": "11", "rafales": "27", "hum": "93", "t_res": "NaN", "rad": "NaN", "rose": "12.7", "pression": "1016.0", "visi": "17"}, "18h": {"temp": "14.1", "precip": "0.2", "vent": "11", "rafales": "24.5", "hum": "92", "t_res": "NaN", "rad": "NaN", "rose": "12.8", "pression": "1015.7", "visi": "8"}, "17h": {"temp": "14.5", "precip": "0.8", "vent": "11", "rafales": "31.7", "hum": "89", "t_res": "NaN", "rad": "11\u00a0", "rose": "12.7", "pression": "1015.5", "visi": "15"}, "16h": {"temp": "15.1", "precip": "0", "vent": "14", "rafales": "35.6", "hum": "84", "t_res": "NaN", "rad": "47\u00a0", "rose": "12.4", "pression": "1015.2", "visi": "17"}, "15h": {"temp": "15.6", "precip": "0", "vent": "14", "rafales": "41", "hum": "87", "t_res": "NaN", "rad": "72\u00a0", "rose": "13.4", "pression": "1014.3", "visi": "12"}, "14h": {"temp": "16.2", "precip": "0", "vent": "18", "rafales": "46.8", "hum": "78", "t_res": "NaN", "rad": "92\u00a0", "rose": "12.4", "pression": "1013.9", "visi": "20"}, "13h": {"temp": "16.0", "precip": "0", "vent": "18", "rafales": "47.9", "hum": "79", "t_res": "NaN", "rad": "97\u00a0", "rose": "12.4", "pression": "1013.6", "visi": "20"}, "12h": {"temp": "15.6", "precip": "0", "vent": "14", "rafales": "46.4", "hum": "80", "t_res": "NaN", "rad": "94\u00a0", "rose": "12.2", "pression": "1013.1", "visi": "20"}, "11h": {"temp": "14.8", "precip": "0", "vent": "22", "rafales": "54.7", "hum": "85", "t_res": "NaN", "rad": "75\u00a0", "rose": "12.3", "pression": "1012.2", "visi": "20"}, "10h": {"temp": "13.7", "precip": "0", "vent": "22", "rafales": "48.6", "hum": "91", "t_res": "NaN", "rad": "56\u00a0", "rose": "12.3", "pression": "1011.1", "visi": "20"}, "09h": {"temp": "12.7", "precip": "0.4", "vent": "14", "rafales": "44.3", "hum": "96", "t_res": "NaN", "rad": "NaN", "rose": "12.1", "pression": "1010.8", "visi": "11"}, "08h": {"temp": "12.2", "precip": "1", "vent": "14", "rafales": "38.5", "hum": "96", "t_res": "NaN", "rad": "NaN", "rose": "11.6", "pression": "1010.3", "visi": "11"}, "07h": {"temp": "11.9", "precip": "0.8", "vent": "15", "rafales": "37.4", "hum": "95", "t_res": "NaN", "rad": "NaN", "rose": "11.1", "pression": "1011.0", "visi": "19"}, "06h": {"temp": "11.6", "precip": "1.6", "vent": "22", "rafales": "39.2", "hum": "95", "t_res": "NaN", "rad": "NaN", "rose": "10.8", "pression": "1011.9", "visi": "12"}, "05h": {"temp": "11.4", "precip": "0.8", "vent": "18", "rafales": "35.6", "hum": "95", "t_res": "NaN", "rad": "NaN", "rose": "10.6", "pression": "1013.0", "visi": "9"}, "04h": {"temp": "11.3", "precip": "0.6", "vent": "18", "rafales": "38.2", "hum": "95", "t_res": "NaN", "rad": "NaN", "rose": "10.5", "pression": "1014.0", "visi": "7"}, "03h": {"temp": "11.3", "precip": "0.2", "vent": "11", "rafales": "32.8", "hum": "93", "t_res": "NaN", "rad": "NaN", "rose": "10.2", "pression": "1015.1", "visi": "15"}, "02h": {"temp": "11.4", "precip": "0", "vent": "14", "rafales": "29.5", "hum": "91", "t_res": "NaN", "rad": "NaN", "rose": "10", "pression": "1015.8", "visi": "19"}, "01h": {"temp": "11.3", "precip": "0", "vent": "14", "rafales": "30.6", "hum": "92", "t_res": "NaN", "rad": "NaN", "rose": "10", "pression": "1016.2", "visi": "20"}}