{"01h": {"temp": "14.4", "precip": "0", "vent": "20", "rafales": "49.3", "hum": "70", "t_res": "NaN", "rad": "NaN", "rose": "9", "pression": "1023.2", "visi": "20"}, "00h": {"temp": "15.4", "precip": "0", "vent": "22", "rafales": "47.9", "hum": "66", "t_res": "NaN", "rad": "NaN", "rose": "9.1", "pression": "1023.2", "visi": "20"}, "23h": {"temp": "16.5", "precip": "0", "vent": "20", "rafales": "46.1", "hum": "65", "t_res": "NaN", "rad": "NaN", "rose": "9.9", "pression": "1022.5", "visi": "20"}, "22h": {"temp": "17.3", "precip": "0", "vent": "20", "rafales": "47.5", "hum": "60", "t_res": "NaN", "rad": "31\u00a0", "rose": "9.5", "pression": "1021.7", "visi": "20"}, "21h": {"temp": "18.8", "precip": "0", "vent": "24", "rafales": "46.8", "hum": "56", "t_res": "NaN", "rad": "92\u00a0", "rose": "9.8", "pression": "1021.2", "visi": "20"}, "20h": {"temp": "19.2", "precip": "0", "vent": "24", "rafales": "50.4", "hum": "52", "t_res": "NaN", "rad": "161\u00a0", "rose": "9.1", "pression": "1020.9", "visi": "20"}, "19h": {"temp": "21.5", "precip": "0", "vent": "22", "rafales": "49", "hum": "51", "t_res": "23.2", "rad": "414\u00a0", "rose": "10.9", "pression": "1020.6", "visi": "20"}, "18h": {"temp": "21.6", "precip": "0", "vent": "24", "rafales": "49.3", "hum": "53", "t_res": "23.6", "rad": "575\u00a0", "rose": "11.6", "pression": "1020.6", "visi": "20"}, "17h": {"temp": "23.0", "precip": "0", "vent": "22", "rafales": "45", "hum": "51", "t_res": "25.4", "rad": "733\u00a0", "rose": "12.3", "pression": "1020.8", "visi": "19"}, "16h": {"temp": "21.8", "precip": "0", "vent": "19", "rafales": "37.8", "hum": "56", "t_res": "24.3", "rad": "417\u00a0", "rose": "12.6", "pression": "1020.9", "visi": "20"}, "15h": {"temp": "21.2", "precip": "0", "vent": "17", "rafales": "37.1", "hum": "60", "t_res": "24", "rad": "558\u00a0", "rose": "13.1", "pression": "1021.3", "visi": "20"}, "14h": {"temp": "19.5", "precip": "0", "vent": "19", "rafales": "37.8", "hum": "68", "t_res": "NaN", "rad": "261\u00a0", "rose": "13.4", "pression": "1021.7", "visi": "20"}, "13h": {"temp": "19.7", "precip": "0", "vent": "19", "rafales": "37.4", "hum": "66", "t_res": "NaN", "rad": "517\u00a0", "rose": "13.2", "pression": "1021.7", "visi": "20"}, "12h": {"temp": "20.4", "precip": "0", "vent": "15", "rafales": "36.4", "hum": "67", "t_res": "23.7", "rad": "569\u00a0", "rose": "14.1", "pression": "1021.5", "visi": "19"}, "11h": {"temp": "18.4", "precip": "0", "vent": "15", "rafales": "36", "hum": "67", "t_res": "NaN", "rad": "353\u00a0", "rose": "12.2", "pression": "1021.5", "visi": "20"}, "10h": {"temp": "18.3", "precip": "0", "vent": "13", "rafales": "29.5", "hum": "64", "t_res": "NaN", "rad": "NaN", "rose": "11.4", "pression": "1021.4", "visi": "20"}, "09h": {"temp": "17.5", "precip": "0", "vent": "15", "rafales": "26.3", "hum": "69", "t_res": "NaN", "rad": "244\u00a0", "rose": "11.7", "pression": "1021.6", "visi": "19"}, "08h": {"temp": "16.3", "precip": "0", "vent": "13", "rafales": "29.9", "hum": "74", "t_res": "NaN", "rad": "186\u00a0", "rose": "11.7", "pression": "1021.4", "visi": "19"}, "07h": {"temp": "15.7", "precip": "0", "vent": "15", "rafales": "26.3", "hum": "76", "t_res": "NaN", "rad": "42\u00a0", "rose": "11.5", "pression": "1021.1", "visi": "20"}, "06h": {"temp": "15.8", "precip": "0", "vent": "11", "rafales": "22.7", "hum": "74", "t_res": "NaN", "rad": "NaN", "rose": "11.2", "pression": "1021.1", "visi": "20"}, "05h": {"temp": "16.3", "precip": "0", "vent": "9", "rafales": "22", "hum": "73", "t_res": "NaN", "rad": "NaN", "rose": "11.4", "pression": "1021.1", "visi": "20"}, "04h": {"temp": "16.7", "precip": "0", "vent": "11", "rafales": "24.1", "hum": "70", "t_res": "NaN", "rad": "NaN", "rose": "11.2", "pression": "1021.2", "visi": "20"}, "03h": {"temp": "17.7", "precip": "0", "vent": "13", "rafales": "29.9", "hum": "67", "t_res": "NaN", "rad": "NaN", "rose": "11.5", "pression": "1021.3", "visi": "20"}, "02h": {"temp": "17.9", "precip": "0", "vent": "13", "rafales": "33.5", "hum": "67", "t_res": "NaN", "rad": "NaN", "rose": "11.7", "pression": "1021.3", "visi": "20"}}