{"01h": {"temp": "17.1", "precip": "0", "vent": "11", "rafales": "18", "hum": "45", "t_res": "NaN", "rad": "NaN", "rose": "5.1", "pression": "1015.9", "visi": "20"}, "00h": {"temp": "18.1", "precip": "0", "vent": "7", "rafales": "25.6", "hum": "43", "t_res": "NaN", "rad": "NaN", "rose": "5.3", "pression": "1016.1", "visi": "20"}, "23h": {"temp": "19.3", "precip": "0", "vent": "11", "rafales": "27.4", "hum": "40", "t_res": "NaN", "rad": "NaN", "rose": "5.4", "pression": "1016.4", "visi": "20"}, "22h": {"temp": "20.5", "precip": "0", "vent": "11", "rafales": "27", "hum": "38", "t_res": "20.5", "rad": "28\u00a0", "rose": "5.7", "pression": "1016.1", "visi": "20"}, "21h": {"temp": "22.0", "precip": "0", "vent": "14", "rafales": "37.8", "hum": "34", "t_res": "22", "rad": "164\u00a0", "rose": "5.4", "pression": "1016.0", "visi": "20"}, "20h": {"temp": "23.6", "precip": "0", "vent": "14", "rafales": "35.3", "hum": "31", "t_res": "23.6", "rad": "333\u00a0", "rose": "5.5", "pression": "1016.0", "visi": "20"}, "19h": {"temp": "24.2", "precip": "0", "vent": "14", "rafales": "35.6", "hum": "30", "t_res": "24.2", "rad": "506\u00a0", "rose": "5.5", "pression": "1016.2", "visi": "20"}, "18h": {"temp": "24.9", "precip": "0", "vent": "11", "rafales": "36.4", "hum": "30", "t_res": "24.9", "rad": "667\u00a0", "rose": "6.1", "pression": "1016.7", "visi": "19"}, "17h": {"temp": "24.8", "precip": "0", "vent": "11", "rafales": "31.3", "hum": "29", "t_res": "24.8", "rad": "797\u00a0", "rose": "5.5", "pression": "1017.3", "visi": "20"}, "16h": {"temp": "24.8", "precip": "0", "vent": "14", "rafales": "37.1", "hum": "28", "t_res": "24.8", "rad": "889\u00a0", "rose": "5", "pression": "1017.7", "visi": "19"}, "15h": {"temp": "24.3", "precip": "0", "vent": "11", "rafales": "31.3", "hum": "35", "t_res": "24.7", "rad": "936\u00a0", "rose": "7.9", "pression": "1018.0", "visi": "20"}, "14h": {"temp": "23.5", "precip": "0", "vent": "14", "rafales": "41.4", "hum": "32", "t_res": "23.5", "rad": "933\u00a0", "rose": "5.8", "pression": "1018.5", "visi": "20"}, "13h": {"temp": "22.3", "precip": "0", "vent": "18", "rafales": "38.9", "hum": "33", "t_res": "22.3", "rad": "881\u00a0", "rose": "5.2", "pression": "1019.2", "visi": "20"}, "12h": {"temp": "22.1", "precip": "0", "vent": "14", "rafales": "46.4", "hum": "38", "t_res": "22.1", "rad": "789\u00a0", "rose": "7.1", "pression": "1019.4", "visi": "20"}, "11h": {"temp": "21.7", "precip": "0", "vent": "14", "rafales": "35.3", "hum": "40", "t_res": "21.9", "rad": "658\u00a0", "rose": "7.5", "pression": "1019.6", "visi": "19"}, "10h": {"temp": "20.1", "precip": "0", "vent": "11", "rafales": "24.8", "hum": "43", "t_res": "20.1", "rad": "NaN", "rose": "7.1", "pression": "1020.1", "visi": "20"}, "09h": {"temp": "18.2", "precip": "0", "vent": "11", "rafales": "23.4", "hum": "46", "t_res": "NaN", "rad": "NaN", "rose": "6.4", "pression": "1020.5", "visi": "20"}, "08h": {"temp": "16.3", "precip": "0", "vent": "7", "rafales": "19.4", "hum": "51", "t_res": "NaN", "rad": "158\u00a0", "rose": "6.1", "pression": "1020.6", "visi": "20"}, "07h": {"temp": "15.0", "precip": "0", "vent": "11", "rafales": "24.5", "hum": "53", "t_res": "NaN", "rad": "25\u00a0", "rose": "5.5", "pression": "1020.8", "visi": "20"}, "06h": {"temp": "14.6", "precip": "0", "vent": "7", "rafales": "21.2", "hum": "54", "t_res": "NaN", "rad": "NaN", "rose": "5.4", "pression": "1020.8", "visi": "20"}, "05h": {"temp": "14.9", "precip": "0", "vent": "7", "rafales": "20.5", "hum": "53", "t_res": "NaN", "rad": "NaN", "rose": "5.4", "pression": "1020.6", "visi": "20"}, "04h": {"temp": "15.6", "precip": "0", "vent": "11", "rafales": "22.7", "hum": "51", "t_res": "NaN", "rad": "NaN", "rose": "5.5", "pression": "1020.4", "visi": "20"}, "03h": {"temp": "15.9", "precip": "0", "vent": "11", "rafales": "22.3", "hum": "51", "t_res": "NaN", "rad": "NaN", "rose": "5.8", "pression": "1020.8", "visi": "20"}, "02h": {"temp": "16.5", "precip": "0", "vent": "7", "rafales": "22", "hum": "49", "t_res": "NaN", "rad": "NaN", "rose": "5.7", "pression": "1021.1", "visi": "20"}}