{"01h": {"temp": "19.5", "precip": "0", "vent": "6", "rafales": "11.9", "hum": "80", "t_res": "NaN", "rad": "NaN", "rose": "16", "pression": "1016.5", "visi": "20"}, "00h": {"temp": "20.2", "precip": "0", "vent": "6", "rafales": "10.8", "hum": "78", "t_res": "24.8", "rad": "NaN", "rose": "16.2", "pression": "1016.6", "visi": "20"}, "23h": {"temp": "20.8", "precip": "0", "vent": "6", "rafales": "11.2", "hum": "75", "t_res": "25.4", "rad": "NaN", "rose": "16.2", "pression": "1016.7", "visi": "20"}, "22h": {"temp": "21.4", "precip": "0", "vent": "4", "rafales": "14", "hum": "72", "t_res": "26", "rad": "NaN", "rose": "16.1", "pression": "1016.5", "visi": "20"}, "21h": {"temp": "22.1", "precip": "0", "vent": "7", "rafales": "17.6", "hum": "69", "t_res": "26.7", "rad": "NaN", "rose": "16.1", "pression": "1016.2", "visi": "20"}, "20h": {"temp": "22.8", "precip": "0", "vent": "7", "rafales": "16.9", "hum": "65", "t_res": "27.2", "rad": "NaN", "rose": "15.9", "pression": "1016.0", "visi": "20"}, "19h": {"temp": "24.0", "precip": "0", "vent": "6", "rafales": "16.2", "hum": "62", "t_res": "28.7", "rad": "NaN", "rose": "16.3", "pression": "1016.2", "visi": "20"}, "18h": {"temp": "24.5", "precip": "0", "vent": "7", "rafales": "19.8", "hum": "59", "t_res": "29", "rad": "231\u00a0", "rose": "16", "pression": "1016.4", "visi": "20"}, "17h": {"temp": "25.3", "precip": "0", "vent": "7", "rafales": "18.7", "hum": "55", "t_res": "29.5", "rad": "550\u00a0", "rose": "15.6", "pression": "1016.9", "visi": "20"}, "16h": {"temp": "24.3", "precip": "0", "vent": "6", "rafales": "13.7", "hum": "59", "t_res": "28.7", "rad": "458\u00a0", "rose": "15.8", "pression": "1017.2", "visi": "20"}, "15h": {"temp": "22.3", "precip": "0", "vent": "4", "rafales": "14.8", "hum": "75", "t_res": "27.9", "rad": "331\u00a0", "rose": "17.7", "pression": "1017.9", "visi": "20"}, "14h": {"temp": "20.3", "precip": "0.4", "vent": "4", "rafales": "10.4", "hum": "83", "t_res": "25.7", "rad": "208\u00a0", "rose": "17.3", "pression": "1018.4", "visi": "19"}, "13h": {"temp": "19.6", "precip": "0", "vent": "6", "rafales": "14.4", "hum": "81", "t_res": "NaN", "rad": "244\u00a0", "rose": "16.2", "pression": "1018.8", "visi": "16"}, "12h": {"temp": "19.5", "precip": "0", "vent": "7", "rafales": "15.5", "hum": "79", "t_res": "NaN", "rad": "200\u00a0", "rose": "15.8", "pression": "1018.8", "visi": "20"}, "11h": {"temp": "18.8", "precip": "0", "vent": "7", "rafales": "16.9", "hum": "83", "t_res": "NaN", "rad": "78\u00a0", "rose": "15.8", "pression": "1018.7", "visi": "20"}, "10h": {"temp": "19.6", "precip": "0", "vent": "4", "rafales": "10.8", "hum": "84", "t_res": "NaN", "rad": "NaN", "rose": "16.8", "pression": "1018.3", "visi": "20"}, "09h": {"temp": "19.0", "precip": "0", "vent": "4", "rafales": "8.3", "hum": "85", "t_res": "NaN", "rad": "NaN", "rose": "16.4", "pression": "1018.0", "visi": "20"}, "08h": {"temp": "18.7", "precip": "0.2", "vent": "4", "rafales": "16.2", "hum": "86", "t_res": "NaN", "rad": "NaN", "rose": "16.3", "pression": "1017.7", "visi": "13"}, "07h": {"temp": "19.2", "precip": "0.2", "vent": "9", "rafales": "19.8", "hum": "80", "t_res": "NaN", "rad": "NaN", "rose": "15.7", "pression": "1017.3", "visi": "0"}, "06h": {"temp": "19.8", "precip": "0", "vent": "6", "rafales": "22.3", "hum": "76", "t_res": "NaN", "rad": "NaN", "rose": "15.4", "pression": "1017.0", "visi": "14"}, "05h": {"temp": "20.6", "precip": "0", "vent": "7", "rafales": "16.6", "hum": "68", "t_res": "24.2", "rad": "NaN", "rose": "14.5", "pression": "1016.9", "visi": "20"}, "04h": {"temp": "20.9", "precip": "0", "vent": "6", "rafales": "19.1", "hum": "65", "t_res": "24.2", "rad": "NaN", "rose": "14.1", "pression": "1017.0", "visi": "20"}, "03h": {"temp": "21.3", "precip": "0", "vent": "9", "rafales": "21.2", "hum": "64", "t_res": "24.7", "rad": "NaN", "rose": "14.2", "pression": "1017.0", "visi": "20"}, "02h": {"temp": "21.8", "precip": "0", "vent": "9", "rafales": "18.7", "hum": "60", "t_res": "24.9", "rad": "NaN", "rose": "13.7", "pression": "1016.8", "visi": "20"}}