{"00h": {"temp": "9.4", "precip": "0 ", "vent": "11", "rafales": "21.6", "hum": "73", "t_res": "7.7", "rad": "NaN", "rose": "4.8", "pression": "1025.7", "visi": "g\" style=\"height:12px\" title=\"+0.4 hPa/3h\"/>"}, "23h": {"temp": "9.8", "precip": "0 ", "vent": "11", "rafales": "22.3", "hum": "72", "t_res": "8.2", "rad": "NaN", "rose": "5", "pression": "1025.6", "visi": "g\" style=\"height:12px\" title=\"+0.2 hPa/3h\"/>"}, "22h": {"temp": "9.9", "precip": "0 ", "vent": "7", "rafales": "19.4", "hum": "75", "t_res": "9", "rad": "NaN", "rose": "5.7", "pression": "1025.5", "visi": "g\" style=\"height:12px\" title=\"+0.1 hPa/3h\"/>"}, "21h": {"temp": "10.1", "precip": "0 ", "vent": "11", "rafales": "20.2", "hum": "75", "t_res": "NaN", "rad": "NaN", "rose": "5.9", "pression": "1025.3", "visi": "g\" style=\"height:12px\" title=\"+0.2 hPa/3h\"/>"}, "20h": {"temp": "10.1", "precip": "0 ", "vent": "7", "rafales": "22.3", "hum": "75", "t_res": "NaN", "rad": "NaN", "rose": "5.9", "pression": "1025.4", "visi": "g\" style=\"height:12px\" title=\"+0.3 hPa/3h\"/>"}, "19h": {"temp": "10.2", "precip": "0 ", "vent": "7", "rafales": "24.8", "hum": "73", "t_res": "NaN", "rad": "NaN", "rose": "5.6", "pression": "1025.4", "visi": "g\" style=\"height:12px\" title=\"+0.2 hPa/3h\"/>"}, "18h": {"temp": "10.5", "precip": "0 ", "vent": "11", "rafales": "28.4", "hum": "72", "t_res": "NaN", "rad": "NaN", "rose": "5.7", "pression": "1025.0", "visi": "g\" style=\"height:12px\" title=\"+0.1 hPa/3h\"/>"}, "17h": {"temp": "10.8", "precip": "0 ", "vent": "7", "rafales": "31", "hum": "68", "t_res": "NaN", "rad": "NaN", "rose": "5.1", "pression": "1025.0", "visi": "g\" style=\"height:12px\" title=\"-0.1 hPa/3h\"/>"}, "16h": {"temp": "11.2", "precip": "0 ", "vent": "11", "rafales": "25.9", "hum": "66", "t_res": "NaN", "rad": "NaN", "rose": "5.1", "pression": "1025.1", "visi": "g\" style=\"height:12px\" title=\"-0.8 hPa/3h\"/>"}, "15h": {"temp": "11.9", "precip": "0 ", "vent": "11", "rafales": "23.8", "hum": "60", "t_res": "NaN", "rad": "428\u00a0", "rose": "4.4", "pression": "1024.9", "visi": "g\" style=\"height:12px\" title=\"-1.6 hPa/3h\"/>"}, "14h": {"temp": "11.8", "precip": "0 ", "vent": "7", "rafales": "18.7", "hum": "61", "t_res": "NaN", "rad": "NaN", "rose": "4.5", "pression": "1025.1", "visi": "g\" style=\"height:12px\" title=\"-1.3 hPa/3h\"/>"}, "13h": {"temp": "10.4", "precip": "0 ", "vent": "7", "rafales": "14.8", "hum": "63", "t_res": "NaN", "rad": "344\u00a0", "rose": "3.7", "pression": "1026.0", "visi": "g\" style=\"height:12px\" title=\"-0.6 hPa/3h\"/>"}, "12h": {"temp": "8.8", "precip": "0 ", "vent": "4", "rafales": "10.1", "hum": "74", "t_res": "8.8", "rad": "NaN", "rose": "4.4", "pression": "1026.6", "visi": "g\" style=\"height:12px\" title=\"+0.4 hPa/3h\"/>"}, "11h": {"temp": "6.3", "precip": "0 ", "vent": "4", "rafales": "15.5", "hum": "80", "t_res": "6.1", "rad": "331\u00a0", "rose": "3.1", "pression": "1026.6", "visi": "ng\" style=\"height:12px\" title=\"+0.7 hPa/3h\"/>"}, "10h": {"temp": "4.1", "precip": "0 ", "vent": "4", "rafales": "12.2", "hum": "88", "t_res": "3.7", "rad": "NaN", "rose": "2.3", "pression": "1026.8", "visi": "ng\" style=\"height:12px\" title=\"+1.2 hPa/3h\"/>"}, "09h": {"temp": "2.9", "precip": "0 ", "vent": "4", "rafales": "7.6", "hum": "92", "t_res": "2.4", "rad": "NaN", "rose": "1.7", "pression": "1026.4", "visi": "ng\" style=\"height:12px\" title=\"+1.2 hPa/3h\"/>"}, "08h": {"temp": "1.9", "precip": "0 ", "vent": "4", "rafales": "9.4", "hum": "94", "t_res": "1.3", "rad": "NaN", "rose": "1", "pression": "1026.1", "visi": "ng\" style=\"height:12px\" title=\"+0.7 hPa/3h\"/>"}, "07h": {"temp": "2.2", "precip": "0 ", "vent": "7", "rafales": "7.6", "hum": "94", "t_res": "0.1", "rad": "NaN", "rose": "1.3", "pression": "1025.6", "visi": "ng\" style=\"height:12px\" title=\"+0.1 hPa/3h\"/>"}, "06h": {"temp": "2.7", "precip": "0 ", "vent": "4", "rafales": "7.2", "hum": "94", "t_res": "2.1", "rad": "NaN", "rose": "1.8", "pression": "1025.2", "visi": "ng\" style=\"height:12px\" title=\"-0.8 hPa/3h\"/>"}, "05h": {"temp": "3.1", "precip": "0 ", "vent": "4", "rafales": "6.5", "hum": "93", "t_res": "2.6", "rad": "NaN", "rose": "2.1", "pression": "1025.3", "visi": "ng\" style=\"height:12px\" title=\"-0.9 hPa/3h\"/>"}, "04h": {"temp": "3.7", "precip": "0 ", "vent": "4", "rafales": "7.6", "hum": "92", "t_res": "3.2", "rad": "NaN", "rose": "2.5", "pression": "1025.5", "visi": "ng\" style=\"height:12px\" title=\"-0.5 hPa/3h\"/>"}, "03h": {"temp": "4.1", "precip": "0 ", "vent": "4", "rafales": "3.6", "hum": "91", "t_res": "3.7", "rad": "NaN", "rose": "2.8", "pression": "1026.0", "visi": "ackground-color:rgb(255,125,0)\">"}, "02h": {"temp": "4.5", "precip": "0 ", "vent": "4", "rafales": "6.5", "hum": "89", "t_res": "4.1", "rad": "NaN", "rose": "2.8", "pression": "1026.2", "visi": "ackground-color:rgb(255,125,0)\">"}, "01h": {"temp": "4.9", "precip": "0 ", "vent": "4", "rafales": "11.2", "hum": "86", "t_res": "4.6", "rad": "NaN", "rose": "2.8", "pression": "1025.9", "visi": "ng\" style=\"height:12px\" title=\"+0.1 hPa/3h\"/>"}}