{"01h": {"temp": "15.1", "precip": "0", "vent": "6", "rafales": "9", "hum": "95", "t_res": "NaN", "rad": "NaN", "rose": "14.3", "pression": "1005.6", "visi": "2.3"}, "00h": {"temp": "15.6", "precip": "0", "vent": "2", "rafales": "8.6", "hum": "94", "t_res": "NaN", "rad": "NaN", "rose": "14.6", "pression": "1005.5", "visi": "4.7"}, "23h": {"temp": "15.7", "precip": "0", "vent": "2", "rafales": "11.5", "hum": "93", "t_res": "NaN", "rad": "NaN", "rose": "14.6", "pression": "1006.1", "visi": "5"}, "22h": {"temp": "15.9", "precip": "0.2", "vent": "7", "rafales": "15.1", "hum": "93", "t_res": "NaN", "rad": "NaN", "rose": "14.8", "pression": "1006.0", "visi": "8"}, "21h": {"temp": "16.1", "precip": "0.6", "vent": "7", "rafales": "15.1", "hum": "92", "t_res": "NaN", "rad": "14\u00a0", "rose": "14.8", "pression": "1005.5", "visi": "10"}, "20h": {"temp": "16.4", "precip": "0.4", "vent": "7", "rafales": "17.6", "hum": "90", "t_res": "NaN", "rad": "67\u00a0", "rose": "14.8", "pression": "1005.3", "visi": "14"}, "19h": {"temp": "16.7", "precip": "0.4", "vent": "7", "rafales": "20.2", "hum": "89", "t_res": "NaN", "rad": "108\u00a0", "rose": "14.9", "pression": "1005.4", "visi": "15"}, "18h": {"temp": "17.1", "precip": "0.2", "vent": "7", "rafales": "15.8", "hum": "87", "t_res": "NaN", "rad": "NaN", "rose": "14.9", "pression": "1005.4", "visi": "17"}, "17h": {"temp": "17.2", "precip": "0", "vent": "6", "rafales": "12.2", "hum": "87", "t_res": "NaN", "rad": "NaN", "rose": "15", "pression": "1005.3", "visi": "19"}, "16h": {"temp": "17.4", "precip": "2", "vent": "4", "rafales": "10.8", "hum": "89", "t_res": "NaN", "rad": "147\u00a0", "rose": "15.6", "pression": "1005.3", "visi": "19"}, "15h": {"temp": "17.1", "precip": "1.2", "vent": "7", "rafales": "21.6", "hum": "85", "t_res": "NaN", "rad": "NaN", "rose": "14.6", "pression": "1005.5", "visi": "9"}, "14h": {"temp": "18.9", "precip": "0", "vent": "9", "rafales": "18.7", "hum": "72", "t_res": "NaN", "rad": "NaN", "rose": "13.7", "pression": "1005.6", "visi": "20"}, "13h": {"temp": "17.5", "precip": "0", "vent": "9", "rafales": "23.4", "hum": "83", "t_res": "NaN", "rad": "NaN", "rose": "14.6", "pression": "1006.0", "visi": "20"}, "12h": {"temp": "16.5", "precip": "0", "vent": "7", "rafales": "26.3", "hum": "86", "t_res": "NaN", "rad": "NaN", "rose": "14.1", "pression": "1006.3", "visi": "8"}, "11h": {"temp": "16.0", "precip": "0", "vent": "11", "rafales": "22.7", "hum": "86", "t_res": "NaN", "rad": "NaN", "rose": "13.7", "pression": "1006.3", "visi": "20"}, "10h": {"temp": "15.9", "precip": "0", "vent": "9", "rafales": "22.7", "hum": "89", "t_res": "NaN", "rad": "NaN", "rose": "14.1", "pression": "1006.2", "visi": "20"}, "09h": {"temp": "15.4", "precip": "0", "vent": "9", "rafales": "18.7", "hum": "91", "t_res": "NaN", "rad": "NaN", "rose": "13.9", "pression": "1006.1", "visi": "18"}, "08h": {"temp": "15.1", "precip": "0", "vent": "9", "rafales": "25.6", "hum": "93", "t_res": "NaN", "rad": "25\u00a0", "rose": "14", "pression": "1005.9", "visi": "17"}, "07h": {"temp": "14.8", "precip": "0", "vent": "7", "rafales": "16.9", "hum": "94", "t_res": "NaN", "rad": "NaN", "rose": "13.8", "pression": "1005.7", "visi": "13"}, "06h": {"temp": "14.7", "precip": "0.2", "vent": "6", "rafales": "21.6", "hum": "94", "t_res": "NaN", "rad": "NaN", "rose": "13.7", "pression": "1005.9", "visi": "12"}, "05h": {"temp": "14.6", "precip": "0", "vent": "7", "rafales": "29.2", "hum": "93", "t_res": "NaN", "rad": "NaN", "rose": "13.5", "pression": "1006.3", "visi": "10"}, "04h": {"temp": "14.8", "precip": "0.2", "vent": "11", "rafales": "26.3", "hum": "94", "t_res": "NaN", "rad": "NaN", "rose": "13.8", "pression": "1006.8", "visi": "10"}, "03h": {"temp": "15.1", "precip": "1.8", "vent": "13", "rafales": "31", "hum": "93", "t_res": "NaN", "rad": "NaN", "rose": "14", "pression": "1007.4", "visi": "4.6"}, "02h": {"temp": "15.4", "precip": "0.6", "vent": "11", "rafales": "29.2", "hum": "93", "t_res": "NaN", "rad": "NaN", "rose": "14.3", "pression": "1007.9", "visi": "4.1"}}