{"01h": {"temp": "14.1", "precip": "0 ", "vent": "18", "rafales": "46.1", "hum": "65", "t_res": "NaN", "rad": "NaN", "rose": "7.6", "pression": "1024.4", "visi": "20"}, "00h": {"temp": "15.2", "precip": "0 ", "vent": "14", "rafales": "38.5", "hum": "62", "t_res": "NaN", "rad": "NaN", "rose": "8", "pression": "1024.1", "visi": "20"}, "23h": {"temp": "16.0", "precip": "0 ", "vent": "18", "rafales": "43.9", "hum": "62", "t_res": "NaN", "rad": "NaN", "rose": "8.7", "pression": "1023.6", "visi": "20"}, "22h": {"temp": "17.5", "precip": "0 ", "vent": "18", "rafales": "42.5", "hum": "56", "t_res": "NaN", "rad": "NaN", "rose": "8.6", "pression": "1023.1", "visi": "20"}, "21h": {"temp": "18.2", "precip": "0 ", "vent": "14", "rafales": "33.1", "hum": "55", "t_res": "NaN", "rad": "NaN", "rose": "9", "pression": "1022.4", "visi": "20"}, "20h": {"temp": "19.2", "precip": "0 ", "vent": "18", "rafales": "35.6", "hum": "52", "t_res": "NaN", "rad": "75\u00a0", "rose": "9.1", "pression": "1021.8", "visi": "20"}, "19h": {"temp": "20.2", "precip": "0 ", "vent": "14", "rafales": "33.1", "hum": "49", "t_res": "21.1", "rad": "242\u00a0", "rose": "9.1", "pression": "1021.6", "visi": "20"}, "18h": {"temp": "21.7", "precip": "0 ", "vent": "14", "rafales": "32", "hum": "47", "t_res": "22.9", "rad": "400\u00a0", "rose": "9.9", "pression": "1021.5", "visi": "20"}, "17h": {"temp": "21.4", "precip": "0 ", "vent": "14", "rafales": "32.8", "hum": "50", "t_res": "22.9", "rad": "511\u00a0", "rose": "10.5", "pression": "1021.5", "visi": "20"}, "16h": {"temp": "22.7", "precip": "0 ", "vent": "11", "rafales": "29.5", "hum": "49", "t_res": "24.6", "rad": "494\u00a0", "rose": "11.4", "pression": "1021.7", "visi": "20"}, "15h": {"temp": "21.6", "precip": "0 ", "vent": "18", "rafales": "27.4", "hum": "52", "t_res": "23.5", "rad": "464\u00a0", "rose": "11.3", "pression": "1022.0", "visi": "20"}, "14h": {"temp": "21.5", "precip": "0 ", "vent": "7", "rafales": "29.9", "hum": "58", "t_res": "24.2", "rad": "583\u00a0", "rose": "12.9", "pression": "1022.2", "visi": "20"}, "13h": {"temp": "20.1", "precip": "0 ", "vent": "14", "rafales": "31", "hum": "62", "t_res": "22.6", "rad": "353\u00a0", "rose": "12.6", "pression": "1022.7", "visi": "20"}, "12h": {"temp": "19.0", "precip": "0 ", "vent": "14", "rafales": "23.8", "hum": "74", "t_res": "NaN", "rad": "100\u00a0", "rose": "14.3", "pression": "1022.9", "visi": "14"}, "11h": {"temp": "18.3", "precip": "0 ", "vent": "11", "rafales": "22", "hum": "78", "t_res": "NaN", "rad": "114\u00a0", "rose": "14.4", "pression": "1022.7", "visi": "14"}, "10h": {"temp": "18.0", "precip": "0 ", "vent": "11", "rafales": "20.2", "hum": "82", "t_res": "NaN", "rad": "92\u00a0", "rose": "14.9", "pression": "1022.4", "visi": "12"}, "09h": {"temp": "17.5", "precip": "0 ", "vent": "11", "rafales": "23", "hum": "84", "t_res": "NaN", "rad": "NaN", "rose": "14.8", "pression": "1022.1", "visi": "13"}, "08h": {"temp": "17.2", "precip": "0 ", "vent": "11", "rafales": "22.3", "hum": "86", "t_res": "NaN", "rad": "NaN", "rose": "14.8", "pression": "1021.7", "visi": "14"}, "07h": {"temp": "17.2", "precip": "0 ", "vent": "11", "rafales": "24.1", "hum": "87", "t_res": "NaN", "rad": "NaN", "rose": "15", "pression": "1021.4", "visi": "9"}, "06h": {"temp": "17.2", "precip": "0 ", "vent": "11", "rafales": "21.6", "hum": "86", "t_res": "NaN", "rad": "NaN", "rose": "14.8", "pression": "1021.2", "visi": "10"}, "05h": {"temp": "17.0", "precip": "0 ", "vent": "11", "rafales": "19.1", "hum": "87", "t_res": "NaN", "rad": "NaN", "rose": "14.8", "pression": "1021.1", "visi": "16"}, "04h": {"temp": "16.9", "precip": "0 ", "vent": "7", "rafales": "28.1", "hum": "86", "t_res": "NaN", "rad": "NaN", "rose": "14.5", "pression": "1021.3", "visi": "17"}, "03h": {"temp": "17.7", "precip": "0 ", "vent": "11", "rafales": "25.2", "hum": "83", "t_res": "NaN", "rad": "NaN", "rose": "14.8", "pression": "1021.3", "visi": "18"}, "02h": {"temp": "18.0", "precip": "0 ", "vent": "14", "rafales": "26.6", "hum": "83", "t_res": "NaN", "rad": "NaN", "rose": "15.1", "pression": "1021.4", "visi": "17"}}