{"00h": {"temp": "4.4", "precip": "0 ", "vent": "7", "rafales": "14", "hum": "57", "t_res": "2.6", "rad": "NaN", "rose": "-3.4", "pression": "1029.5", "visi": "g\" style=\"height:12px\" title=\"+0.3 hPa/3h\"/>"}, "23h": {"temp": "4.6", "precip": "0 ", "vent": "4", "rafales": "16.9", "hum": "59", "t_res": "4.2", "rad": "NaN", "rose": "-2.7", "pression": "1029.4", "visi": "g\" style=\"height:12px\" title=\"+0.4 hPa/3h\"/>"}, "22h": {"temp": "4.6", "precip": "0 ", "vent": "7", "rafales": "20.5", "hum": "62", "t_res": "2.8", "rad": "NaN", "rose": "-2.1", "pression": "1029.3", "visi": "g\" style=\"height:12px\" title=\"+0.4 hPa/3h\"/>"}, "21h": {"temp": "4.8", "precip": "0 ", "vent": "11", "rafales": "21.2", "hum": "64", "t_res": "2.2", "rad": "NaN", "rose": "-1.4", "pression": "1029.2", "visi": "g\" style=\"height:12px\" title=\"+0.4 hPa/3h\"/>"}, "20h": {"temp": "4.9", "precip": "0 ", "vent": "11", "rafales": "21.6", "hum": "64", "t_res": "2.3", "rad": "NaN", "rose": "-1.3", "pression": "1029.0", "visi": "g\" style=\"height:12px\" title=\"+0.4 hPa/3h\"/>"}, "19h": {"temp": "5.0", "precip": "0 ", "vent": "14", "rafales": "25.6", "hum": "71", "t_res": "1.8", "rad": "NaN", "rose": "0.2", "pression": "1028.9", "visi": "g\" style=\"height:12px\" title=\"+0.4 hPa/3h\"/>"}, "18h": {"temp": "5.1", "precip": "0 ", "vent": "11", "rafales": "27", "hum": "61", "t_res": "2.6", "rad": "NaN", "rose": "-1.8", "pression": "1028.8", "visi": "g\" style=\"height:12px\" title=\"+0.4 hPa/3h\"/>"}, "17h": {"temp": "5.0", "precip": "0 ", "vent": "14", "rafales": "32.8", "hum": "66", "t_res": "1.8", "rad": "11\u00a0", "rose": "-0.8", "pression": "1028.6", "visi": "g\" style=\"height:12px\" title=\"+0.3 hPa/3h\"/>"}, "16h": {"temp": "5.2", "precip": "0 ", "vent": "14", "rafales": "35.6", "hum": "66", "t_res": "2", "rad": "58\u00a0", "rose": "-0.6", "pression": "1028.5", "visi": "g\" style=\"height:12px\" title=\"-0.4 hPa/3h\"/>"}, "15h": {"temp": "5.5", "precip": "0 ", "vent": "18", "rafales": "34.6", "hum": "66", "t_res": "1.9", "rad": "108\u00a0", "rose": "-0.4", "pression": "1028.4", "visi": "g\" style=\"height:12px\" title=\"-0.8 hPa/3h\"/>"}, "14h": {"temp": "5.2", "precip": "0 ", "vent": "14", "rafales": "33.8", "hum": "69", "t_res": "2", "rad": "161\u00a0", "rose": "0", "pression": "1028.3", "visi": "g\" style=\"height:12px\" title=\"-0.9 hPa/3h\"/>"}, "13h": {"temp": "5.0", "precip": "0 ", "vent": "18", "rafales": "27", "hum": "69", "t_res": "1.3", "rad": "206\u00a0", "rose": "-0.2", "pression": "1028.9", "visi": "g\" style=\"height:12px\" title=\"+0.1 hPa/3h\"/>"}, "12h": {"temp": "4.2", "precip": "0 ", "vent": "14", "rafales": "26.6", "hum": "72", "t_res": "0.8", "rad": "136\u00a0", "rose": "-0.4", "pression": "1029.2", "visi": "g\" style=\"height:12px\" title=\"+0.8 hPa/3h\"/>"}, "11h": {"temp": "3.5", "precip": "0 ", "vent": "11", "rafales": "25.2", "hum": "74", "t_res": "0.7", "rad": "75\u00a0", "rose": "-0.7", "pression": "1029.2", "visi": "g\" style=\"height:12px\" title=\"+1.2 hPa/3h\"/>"}, "10h": {"temp": "3.0", "precip": "0 ", "vent": "11", "rafales": "24.1", "hum": "77", "t_res": "0.1", "rad": "19\u00a0", "rose": "-0.6", "pression": "1028.8", "visi": "g\" style=\"height:12px\" title=\"+1.2 hPa/3h\"/>"}, "09h": {"temp": "2.9", "precip": "0 ", "vent": "14", "rafales": "24.1", "hum": "77", "t_res": "-0.8", "rad": "NaN", "rose": "-0.7", "pression": "1028.4", "visi": "g\" style=\"height:12px\" title=\"+1.1 hPa/3h\"/>"}, "08h": {"temp": "2.4", "precip": "0 ", "vent": "14", "rafales": "25.9", "hum": "77", "t_res": "-1.4", "rad": "NaN", "rose": "-1.2", "pression": "1028.1", "visi": "g\" style=\"height:12px\" title=\"+0.9 hPa/3h\"/>"}, "07h": {"temp": "2.2", "precip": "0 ", "vent": "14", "rafales": "31", "hum": "79", "t_res": "-1.6", "rad": "NaN", "rose": "-1.1", "pression": "1027.7", "visi": "g\" style=\"height:12px\" title=\"+0.4 hPa/3h\"/>"}, "06h": {"temp": "2.4", "precip": "0 ", "vent": "18", "rafales": "27.4", "hum": "78", "t_res": "-2", "rad": "NaN", "rose": "-1", "pression": "1027.4", "visi": "g\" style=\"height:12px\" title=\"+0.3 hPa/3h\"/>"}, "05h": {"temp": "2.7", "precip": "0 ", "vent": "14", "rafales": "24.8", "hum": "77", "t_res": "-1", "rad": "NaN", "rose": "-0.9", "pression": "1027.1", "visi": "g\" style=\"height:12px\" title=\"+0.3 hPa/3h\"/>"}, "04h": {"temp": "2.8", "precip": "0 ", "vent": "14", "rafales": "29.2", "hum": "77", "t_res": "-0.9", "rad": "NaN", "rose": "-0.8", "pression": "1027.2", "visi": "g\" style=\"height:12px\" title=\"+0.6 hPa/3h\"/>"}, "03h": {"temp": "3.0", "precip": "0 ", "vent": "11", "rafales": "27.7", "hum": "78", "t_res": "0.1", "rad": "NaN", "rose": "-0.5", "pression": "1027.0", "visi": "g\" style=\"height:12px\" title=\"+0.6 hPa/3h\"/>"}, "02h": {"temp": "3.0", "precip": "0 ", "vent": "14", "rafales": "30.6", "hum": "77", "t_res": "-0.6", "rad": "NaN", "rose": "-0.6", "pression": "1026.8", "visi": "g\" style=\"height:12px\" title=\"+0.9 hPa/3h\"/>"}, "01h": {"temp": "3.4", "precip": "0 ", "vent": "14", "rafales": "32", "hum": "77", "t_res": "-0.2", "rad": "NaN", "rose": "-0.3", "pression": "1026.6", "visi": "g\" style=\"height:12px\" title=\"+0.8 hPa/3h\"/>"}}