{"00h": {"temp": "9.8", "precip": "0", "vent": "7", "rafales": "24.8", "hum": "84", "t_res": "8.9", "rad": "NaN", "rose": "7.2", "pression": "1003.1", "visi": "19"}, "23h": {"temp": "9.7", "precip": "0", "vent": "11", "rafales": "32", "hum": "79", "t_res": "8", "rad": "NaN", "rose": "6.2", "pression": "1003.6", "visi": "17"}, "22h": {"temp": "10.3", "precip": "0", "vent": "14", "rafales": "40.7", "hum": "73", "t_res": "NaN", "rad": "NaN", "rose": "5.7", "pression": "1003.5", "visi": "18"}, "21h": {"temp": "10.7", "precip": "0", "vent": "18", "rafales": "43.2", "hum": "71", "t_res": "NaN", "rad": "NaN", "rose": "5.7", "pression": "1003.3", "visi": "18"}, "20h": {"temp": "11.4", "precip": "0", "vent": "14", "rafales": "44.3", "hum": "78", "t_res": "NaN", "rad": "NaN", "rose": "7.7", "pression": "1002.9", "visi": "19"}, "19h": {"temp": "11.5", "precip": "0", "vent": "22", "rafales": "56.5", "hum": "76", "t_res": "NaN", "rad": "NaN", "rose": "7.4", "pression": "1001.9", "visi": "19"}, "18h": {"temp": "11.5", "precip": "0", "vent": "18", "rafales": "49.3", "hum": "77", "t_res": "NaN", "rad": "NaN", "rose": "7.6", "pression": "1001.2", "visi": "20"}, "17h": {"temp": "11.6", "precip": "2.6", "vent": "25", "rafales": "72", "hum": "79", "t_res": "NaN", "rad": "NaN", "rose": "8.1", "pression": "1001.2", "visi": "16"}, "16h": {"temp": "14.7", "precip": "0", "vent": "25", "rafales": "66.2", "hum": "81", "t_res": "NaN", "rad": "33\u00a0", "rose": "11.5", "pression": ">999.5", "visi": "19"}, "15h": {"temp": "14.5", "precip": "0", "vent": "18", "rafales": "55.4", "hum": "82", "t_res": "NaN", "rad": "56\u00a0", "rose": "11.5", "pression": "1000.0", "visi": "20"}, "14h": {"temp": "14.6", "precip": "0", "vent": "29", "rafales": "69.5", "hum": "82", "t_res": "NaN", "rad": "53\u00a0", "rose": "11.6", "pression": "1000.4", "visi": "19"}, "13h": {"temp": "14.5", "precip": "0", "vent": "22", "rafales": "60.8", "hum": "83", "t_res": "NaN", "rad": "69\u00a0", "rose": "11.6", "pression": "1001.2", "visi": "20"}, "12h": {"temp": "14.5", "precip": "0", "vent": "25", "rafales": "54.7", "hum": "82", "t_res": "NaN", "rad": "42\u00a0", "rose": "11.5", "pression": "1001.8", "visi": "20"}, "11h": {"temp": "14.3", "precip": "0.2", "vent": "25", "rafales": "65.5", "hum": "83", "t_res": "NaN", "rad": "11\u00a0", "rose": "11.4", "pression": "1001.7", "visi": "20"}, "10h": {"temp": "13.9", "precip": "0", "vent": "25", "rafales": "62.6", "hum": "85", "t_res": "NaN", "rad": "NaN", "rose": "11.4", "pression": "1001.0", "visi": "20"}, "09h": {"temp": "13.4", "precip": "0.6", "vent": "29", "rafales": "63", "hum": "89", "t_res": "NaN", "rad": "NaN", "rose": "11.6", "pression": "1000.5", "visi": "19"}, "08h": {"temp": "13.0", "precip": "0.2", "vent": "22", "rafales": "50.4", "hum": "94", "t_res": "NaN", "rad": "NaN", "rose": "12.1", "pression": "1000.7", "visi": "17"}, "07h": {"temp": "10.6", "precip": "1.4", "vent": "11", "rafales": "27.4", "hum": "97", "t_res": "NaN", "rad": "NaN", "rose": "10.1", "pression": "1001.5", "visi": "8"}, "06h": {"temp": "9.4", "precip": "0.8", "vent": "7", "rafales": "22.3", "hum": "96", "t_res": "8.4", "rad": "NaN", "rose": "8.8", "pression": "1002.6", "visi": "5"}, "05h": {"temp": "9.1", "precip": "0.4", "vent": "11", "rafales": "22.7", "hum": "96", "t_res": "7.3", "rad": "NaN", "rose": "8.5", "pression": "1003.5", "visi": "6"}, "04h": {"temp": "8.8", "precip": "0.2", "vent": "11", "rafales": "19.8", "hum": "96", "t_res": "7", "rad": "NaN", "rose": "8.2", "pression": "1004.8", "visi": "4.1"}, "03h": {"temp": "8.5", "precip": "0.2", "vent": "7", "rafales": "18.4", "hum": "95", "t_res": "7.4", "rad": "NaN", "rose": "7.7", "pression": "1006.1", "visi": "5"}, "02h": {"temp": "8.3", "precip": "0", "vent": "7", "rafales": "15.8", "hum": "94", "t_res": "7.1", "rad": "NaN", "rose": "7.4", "pression": "1006.3", "visi": "12"}, "01h": {"temp": "8.3", "precip": "1", "vent": "7", "rafales": "20.2", "hum": "93", "t_res": "7.1", "rad": "NaN", "rose": "7.2", "pression": "1007.7", "visi": "9"}}